universalSOAP/__init__.py
universalSOAP/hypers.py
universalSOAP/cli/write_descriptor_quantities.py
universalSOAP-0.1.1.dist-info/LICENSE
universalSOAP-0.1.1.dist-info/METADATA
universalSOAP-0.1.1.dist-info/WHEEL
universalSOAP-0.1.1.dist-info/entry_points.txt
universalSOAP-0.1.1.dist-info/top_level.txt
universalSOAP-0.1.1.dist-info/RECORD
