Metadata-Version: 2.1
Name: universalSOAP
Version: 0.1.1
License: GNU GENERAL PUBLIC LICENSE
Requires-Python: >=3.9
License-File: LICENSE
